README.md
setup.py
clear_screen/__init__.py
clear_screen/clear_screen.py
clear_screen.egg-info/PKG-INFO
clear_screen.egg-info/SOURCES.txt
clear_screen.egg-info/dependency_links.txt
clear_screen.egg-info/top_level.txt