Metadata-Version: 2.1
Name: clear-screen
Version: 0.1.5
Summary: A simple class for clearing a Python Interpreter Shell
Home-page: https://github.com/rootVIII/clear_screen
Author: James Loye Colley
License: UNKNOWN
Platform: UNKNOWN
Classifier: Programming Language :: Python :: 3
Classifier: License :: OSI Approved :: MIT License
Classifier: Operating System :: OS Independent
